patent/__init__.py
patent/claim.py
patent/patent.py
patent-0.0.1.dist-info/LICENSE
patent-0.0.1.dist-info/METADATA
patent-0.0.1.dist-info/WHEEL
patent-0.0.1.dist-info/top_level.txt
patent-0.0.1.dist-info/RECORD
