Metadata-Version: 2.1
Name: patent
Version: 0.0.1
Summary: A set of tools for extracting info from a patent
Home-page: https://github.com/56kyle/window_input
Author: Kyle Oliver
Author-email: 56kyleoliver@gmail.com
License: UNKNOWN
Platform: UNKNOWN
Classifier: Programming Language :: Python :: 3
Classifier: License :: OSI Approved :: MIT License
Requires-Dist: requests
Requires-Dist: bs4
